eplines/__init__.py
eplines/eplines.py
eplines-0.1.dist-info/LICENSE
eplines-0.1.dist-info/METADATA
eplines-0.1.dist-info/WHEEL
eplines-0.1.dist-info/top_level.txt
eplines-0.1.dist-info/RECORD
