Metadata-Version: 2.1
Name: eplines
Version: 0.1
Summary: Heatmaps of empirical and exceedance probability of many (time-)series.
Home-page: https://github.com/rhkarls/eplines
License: MIT
Project-URL: Bug Tracker, https://github.com/rhkarls/eplines/issues
Classifier: License :: OSI Approved :: MIT License
Classifier: Programming Language :: Python :: 3
Classifier: Programming Language :: Python :: 3.8
Classifier: Programming Language :: Python :: 3.9
Classifier: Programming Language :: Python :: 3.10
Requires-Python: >=3.8
License-File: LICENSE
Requires-Dist: numpy
Requires-Dist: matplotlib
